tuitorial/__init__.py
tuitorial/_version.py
tuitorial/app.py
tuitorial/helpers.py
tuitorial/highlighting.py
tuitorial/parse_yaml.py
tuitorial/py.typed
tuitorial/widgets.py
tuitorial-0.15.0.dist-info/METADATA
tuitorial-0.15.0.dist-info/WHEEL
tuitorial-0.15.0.dist-info/entry_points.txt
tuitorial-0.15.0.dist-info/licenses/AUTHORS.md
tuitorial-0.15.0.dist-info/licenses/LICENSE
tuitorial-0.15.0.dist-info/RECORD
