Metadata-Version: 2.4
Name: tuitorial
Version: 0.15.0
Summary: A tutorial presentation tool using Textual
Project-URL: homepage, https://tuitorial.readthedocs.io/
Project-URL: documentation, https://tuitorial.readthedocs.io/
Project-URL: repository, https://github.com/basnijholt/tuitorial
Maintainer-email: Bas Nijholt <bas@nijho.lt>
License: MIT
License-File: AUTHORS.md
License-File: LICENSE
Classifier: Development Status :: 4 - Beta
Classifier: Environment :: Console
Classifier: Environment :: Console :: Curses
Classifier: Intended Audience :: Developers
Classifier: Intended Audience :: Education
Classifier: Intended Audience :: End Users/Desktop
Classifier: License :: OSI Approved :: MIT License
Classifier: Operating System :: OS Independent
Classifier: Programming Language :: Python
Classifier: Programming Language :: Python :: 3
Classifier: Programming Language :: Python :: 3.10
Classifier: Programming Language :: Python :: 3.11
Classifier: Programming Language :: Python :: 3.12
Classifier: Programming Language :: Python :: 3.13
Classifier: Topic :: Education
Classifier: Topic :: Education :: Computer Aided Instruction (CAI)
Classifier: Topic :: Software Development
Classifier: Topic :: Software Development :: Documentation
Classifier: Topic :: Software Development :: Libraries :: Python Modules
Classifier: Topic :: Text Processing :: Markup
Classifier: Topic :: Utilities
Classifier: Typing :: Typed
Requires-Python: >=3.10
Requires-Dist: chardet>=5.2.0
Requires-Dist: pyfiglet>=1.0.2
Requires-Dist: pyyaml>=6.0.2
Requires-Dist: rich
Requires-Dist: textual
Requires-Dist: textual-image[textual]>=0.7.0
Requires-Dist: watchfiles>=1.0.3
